kisesi/__init__.py
kisesi-0.4.1.dist-info/METADATA
kisesi-0.4.1.dist-info/WHEEL
kisesi-0.4.1.dist-info/licenses/LICENSE
kisesi-0.4.1.dist-info/RECORD
