Metadata-Version: 2.4
Name: kisesi
Version: 0.4.1
Summary: Light wrapper around Python's `logging` built-in module.
Project-URL: Repository, https://github.com/eeriemyxi/kisesi
Project-URL: Issues, https://github.com/eeriemyxi/kisesi/issues
Author-email: myxi <myxi@envs.net>
License: Copyright (c) 2024 myxi@envs.net
License-File: LICENSE
Keywords: color,logging,python,wrapper
Requires-Python: >=3.6
